{
  "generated_at": "2026-07-10T22:00:24.416536+00:00",
  "min_pp_threshold": 0.3,
  "top_movers_up": [
    {
      "team": "France",
      "static": 0.09691999999999999,
      "live": 0.24428,
      "delta_pp": 14.735999999999999
    },
    {
      "team": "Argentina",
      "static": 0.21164,
      "live": 0.2884,
      "delta_pp": 7.675999999999999
    },
    {
      "team": "England",
      "static": 0.06348000000000001,
      "live": 0.11707999999999999,
      "delta_pp": 5.359999999999998
    },
    {
      "team": "Spain",
      "static": 0.26532,
      "live": 0.30663999999999997,
      "delta_pp": 4.131999999999997
    },
    {
      "team": "Norway",
      "static": 0.015160000000000002,
      "live": 0.03012,
      "delta_pp": 1.496
    },
    {
      "team": "Switzerland",
      "static": 0.01032,
      "live": 0.01348,
      "delta_pp": 0.3160000000000001
    }
  ],
  "top_movers_down": [
    {
      "team": "Colombia",
      "static": 0.050960000000000005,
      "live": 0.0,
      "delta_pp": -5.096
    },
    {
      "team": "Brazil",
      "static": 0.04028,
      "live": 0.0,
      "delta_pp": -4.0280000000000005
    },
    {
      "team": "Portugal",
      "static": 0.03828,
      "live": 0.0,
      "delta_pp": -3.8280000000000003
    },
    {
      "team": "Netherlands",
      "static": 0.0304,
      "live": 0.0,
      "delta_pp": -3.04
    },
    {
      "team": "Germany",
      "static": 0.027000000000000003,
      "live": 0.0,
      "delta_pp": -2.7
    },
    {
      "team": "Ecuador",
      "static": 0.02652,
      "live": 0.0,
      "delta_pp": -2.6519999999999997
    },
    {
      "team": "Mexico",
      "static": 0.01576,
      "live": 0.0,
      "delta_pp": -1.576
    },
    {
      "team": "Morocco",
      "static": 0.015040000000000001,
      "live": 0.0,
      "delta_pp": -1.5040000000000002
    },
    {
      "team": "Croatia",
      "static": 0.013040000000000001,
      "live": 0.0,
      "delta_pp": -1.304
    },
    {
      "team": "Turkey",
      "static": 0.012839999999999999,
      "live": 0.0,
      "delta_pp": -1.2839999999999998
    }
  ],
  "all_movers": [
    {
      "team": "France",
      "static": 0.09691999999999999,
      "live": 0.24428,
      "delta_pp": 14.735999999999999
    },
    {
      "team": "Argentina",
      "static": 0.21164,
      "live": 0.2884,
      "delta_pp": 7.675999999999999
    },
    {
      "team": "England",
      "static": 0.06348000000000001,
      "live": 0.11707999999999999,
      "delta_pp": 5.359999999999998
    },
    {
      "team": "Colombia",
      "static": 0.050960000000000005,
      "live": 0.0,
      "delta_pp": -5.096
    },
    {
      "team": "Spain",
      "static": 0.26532,
      "live": 0.30663999999999997,
      "delta_pp": 4.131999999999997
    },
    {
      "team": "Brazil",
      "static": 0.04028,
      "live": 0.0,
      "delta_pp": -4.0280000000000005
    },
    {
      "team": "Portugal",
      "static": 0.03828,
      "live": 0.0,
      "delta_pp": -3.8280000000000003
    },
    {
      "team": "Netherlands",
      "static": 0.0304,
      "live": 0.0,
      "delta_pp": -3.04
    },
    {
      "team": "Germany",
      "static": 0.027000000000000003,
      "live": 0.0,
      "delta_pp": -2.7
    },
    {
      "team": "Ecuador",
      "static": 0.02652,
      "live": 0.0,
      "delta_pp": -2.6519999999999997
    },
    {
      "team": "Mexico",
      "static": 0.01576,
      "live": 0.0,
      "delta_pp": -1.576
    },
    {
      "team": "Morocco",
      "static": 0.015040000000000001,
      "live": 0.0,
      "delta_pp": -1.5040000000000002
    },
    {
      "team": "Norway",
      "static": 0.015160000000000002,
      "live": 0.03012,
      "delta_pp": 1.496
    },
    {
      "team": "Croatia",
      "static": 0.013040000000000001,
      "live": 0.0,
      "delta_pp": -1.304
    },
    {
      "team": "Turkey",
      "static": 0.012839999999999999,
      "live": 0.0,
      "delta_pp": -1.2839999999999998
    },
    {
      "team": "Belgium",
      "static": 0.01212,
      "live": 0.0,
      "delta_pp": -1.212
    },
    {
      "team": "Japan",
      "static": 0.00988,
      "live": 0.0,
      "delta_pp": -0.988
    },
    {
      "team": "Uruguay",
      "static": 0.00924,
      "live": 0.0,
      "delta_pp": -0.924
    },
    {
      "team": "Canada",
      "static": 0.00664,
      "live": 0.0,
      "delta_pp": -0.664
    },
    {
      "team": "Iran",
      "static": 0.0044399999999999995,
      "live": 0.0,
      "delta_pp": -0.44399999999999995
    },
    {
      "team": "Senegal",
      "static": 0.00416,
      "live": 0.0,
      "delta_pp": -0.416
    },
    {
      "team": "South Korea",
      "static": 0.0035199999999999997,
      "live": 0.0,
      "delta_pp": -0.352
    },
    {
      "team": "Australia",
      "static": 0.00324,
      "live": 0.0,
      "delta_pp": -0.32399999999999995
    },
    {
      "team": "Switzerland",
      "static": 0.01032,
      "live": 0.01348,
      "delta_pp": 0.3160000000000001
    }
  ]
}